sliger/__init__.py
sliger-0.1.0.dist-info/METADATA
sliger-0.1.0.dist-info/WHEEL
sliger-0.1.0.dist-info/entry_points.txt
sliger-0.1.0.dist-info/RECORD
