Metadata-Version: 2.1
Name: sliger
Version: 0.1.0
Summary: Slide the power of Python (and Jinja2) into Google Slides
License: Apache 2.0
Author: Giulio Piccolo
Author-email: gipiccol@cisco.com
Requires-Python: >=3.10,<4.0
Classifier: License :: Other/Proprietary License
Classifier: Programming Language :: Python :: 3
Classifier: Programming Language :: Python :: 3.10
Classifier: Programming Language :: Python :: 3.11
Requires-Dist: google (>=3.0.0,<4.0.0)
Requires-Dist: google-api-python-client (>=2.87.0,<3.0.0)
Requires-Dist: google-auth (==2.19.0)
Requires-Dist: google-auth-httplib2 (>=0.1.0,<0.2.0)
Requires-Dist: google-auth-oauthlib (>=1.0.0,<2.0.0)
Requires-Dist: jinja2 (>=3.1.2,<4.0.0)
Requires-Dist: toml (>=0.10.2,<0.11.0)
Requires-Dist: typer (>=0.9.0,<0.10.0)
